cjy/__init__.py
cjy/generator.py
cjy-1.6.dist-info/LICENSE
cjy-1.6.dist-info/METADATA
cjy-1.6.dist-info/WHEEL
cjy-1.6.dist-info/top_level.txt
cjy-1.6.dist-info/RECORD
